rm_my_package/__init__.py
rm_my_package/my_module.py
rm_my_package/data/sample.txt
rm_my_package-0.0.1.dist-info/LICENSE.txt
rm_my_package-0.0.1.dist-info/METADATA
rm_my_package-0.0.1.dist-info/WHEEL
rm_my_package-0.0.1.dist-info/top_level.txt
rm_my_package-0.0.1.dist-info/zip-safe
rm_my_package-0.0.1.dist-info/RECORD
