Metadata-Version: 2.1
Name: rm-my-package
Version: 0.0.1
Summary: Demo
Home-page: UNKNOWN
Author: Ramya M
Author-email: ramya.mrao13@gmail.com
License: BSD 3-Clause License
Project-URL: Source, https://github.com/RamyaM12/publish_package_fun.git
Keywords: rm,fun
Platform: UNKNOWN
Classifier: Programming Language :: Python :: 3
